odoo/addons/pos_unavailable_product_friendly_error/README.rst
odoo/addons/pos_unavailable_product_friendly_error/__init__.py
odoo/addons/pos_unavailable_product_friendly_error/__manifest__.py
odoo/addons/pos_unavailable_product_friendly_error/i18n/fr.po
odoo/addons/pos_unavailable_product_friendly_error/i18n/it.po
odoo/addons/pos_unavailable_product_friendly_error/i18n/pos_unavailable_product_friendly_error.pot
odoo/addons/pos_unavailable_product_friendly_error/readme/CONTRIBUTORS.rst
odoo/addons/pos_unavailable_product_friendly_error/readme/DESCRIPTION.rst
odoo/addons/pos_unavailable_product_friendly_error/static/description/icon.png
odoo/addons/pos_unavailable_product_friendly_error/static/description/index.html
odoo/addons/pos_unavailable_product_friendly_error/static/description/pos_front_end_popup.png
odoo/addons/pos_unavailable_product_friendly_error/static/src/js/models.js
odoo/addons/pos_unavailable_product_friendly_error/views/templates.xml
odoo12_addon_pos_unavailable_product_friendly_error-12.0.1.0.1.99.dev8.dist-info/METADATA
odoo12_addon_pos_unavailable_product_friendly_error-12.0.1.0.1.99.dev8.dist-info/WHEEL
odoo12_addon_pos_unavailable_product_friendly_error-12.0.1.0.1.99.dev8.dist-info/top_level.txt
odoo12_addon_pos_unavailable_product_friendly_error-12.0.1.0.1.99.dev8.dist-info/RECORD
